kodexa_document/connectors.py
kodexa_document/model.py
kodexa_document/persistence.py
kodexa_document/persistence_models.py
kodexa_document/selectors/__init__.py
kodexa_document/selectors/ast.py
kodexa_document/selectors/error.py
kodexa_document/selectors/kodexa-ast-visitor.py
kodexa_document/selectors/parser.py
kodexa_document/selectors/resources/KodexaSelector.interp
kodexa_document/selectors/resources/KodexaSelector.tokens
kodexa_document/selectors/resources/KodexaSelectorLexer.interp
kodexa_document/selectors/resources/KodexaSelectorLexer.py
kodexa_document/selectors/resources/KodexaSelectorLexer.tokens
kodexa_document/selectors/resources/KodexaSelectorListener.py
kodexa_document/selectors/resources/KodexaSelectorParser.py
kodexa_document/selectors/resources/KodexaSelectorVisitor.py
kodexa_document/selectors/visitor.py
kodexa_document/steps.py
kodexa_document-8.0.18462071415.dist-info/METADATA
kodexa_document-8.0.18462071415.dist-info/WHEEL
kodexa_document-8.0.18462071415.dist-info/RECORD
